LICENSE.txt
MANIFEST.in
README.md
python2matlab_notes.txt
setup.py
licenses/oct2py.txt
licenses/ompc.txt
pyopy/__init__.py
pyopy/backend_mathworks.py
pyopy/backend_matlab_wrapper.py
pyopy/backend_oct2py.py
pyopy/backend_pymatbridge.py
pyopy/base.py
pyopy/code.py
pyopy/config.py
pyopy/misc.py
pyopy.egg-info/PKG-INFO
pyopy.egg-info/SOURCES.txt
pyopy.egg-info/dependency_links.txt
pyopy.egg-info/entry_points.txt
pyopy.egg-info/requires.txt
pyopy.egg-info/top_level.txt
pyopy/externals/__init__.py
pyopy/externals/ompc/__init__.py
pyopy/externals/ompc/lex.py
pyopy/externals/ompc/ompcply.py
pyopy/externals/ompc/parsetab.py
pyopy/externals/ompc/yacc.py
pyopy/externals/toolboxes/pyopy/portable_pid.m
pyopy/hctsa/__init__.py
pyopy/hctsa/hctsa.py
pyopy/hctsa/hctsa_benchmark.py
pyopy/hctsa/hctsa_bindings.py
pyopy/hctsa/hctsa_bindings_gen.py
pyopy/hctsa/hctsa_catalog.py
pyopy/hctsa/hctsa_cli.py
pyopy/hctsa/hctsa_config.py
pyopy/hctsa/hctsa_data.py
pyopy/hctsa/hctsa_install.py
pyopy/hctsa/hctsa_transformers.py
pyopy/hctsa/tests/__init__.py
pyopy/hctsa/tests/test_bindings.py
pyopy/minioct2py/__init__.py
pyopy/minioct2py/compat.py
pyopy/minioct2py/matread.py
pyopy/minioct2py/matwrite.py
pyopy/minioct2py/utils.py
pyopy/tests/__init__.py
pyopy/tests/test_engines.py
pyopy/tests/test_parsing.py