Metadata-Version: 1.1
Name: pyopy
Version: 0.1.0
Summary: PYthon->Octave->PYthon: Tools to pythonize matlab/octave libraries
Home-page: https://github.com/strawlab/pyopy
Author: Santi Villalba
Author-email: sdvillal@gmail.com
License: BSD 3 clause
Platform: UNKNOWN
Classifier: Intended Audience :: Science/Research
Classifier: Intended Audience :: Developers
Classifier: License :: OSI Approved :: BSD License
Classifier: Programming Language :: Python
Classifier: Topic :: Software Development
Classifier: Topic :: Scientific/Engineering
Classifier: Operating System :: MacOS
Classifier: Operating System :: POSIX :: Linux
Classifier: Programming Language :: Python :: 2.7
Requires: numpy
Requires: scipy
Requires: pandas
Requires: joblib
Requires: argh
Requires: whatami
Requires: lockfile
